README.md
setup.cfg
setup.py
aiopika_macrobase/__init__.py
aiopika_macrobase/config.py
aiopika_macrobase/driver.py
aiopika_macrobase/endpoint.py
aiopika_macrobase/exceptions.py
aiopika_macrobase/hook.py
aiopika_macrobase/method.py
aiopika_macrobase/result.py
aiopika_macrobase/router.py
aiopika_macrobase/serializers.py
aiopika_macrobase.egg-info/PKG-INFO
aiopika_macrobase.egg-info/SOURCES.txt
aiopika_macrobase.egg-info/dependency_links.txt
aiopika_macrobase.egg-info/requires.txt
aiopika_macrobase.egg-info/top_level.txt
aiopika_macrobase/rpc/__init__.py
aiopika_macrobase/rpc/client.py
aiopika_macrobase/rpc/config.py
aiopika_macrobase/rpc/driver.py
aiopika_macrobase/rpc/endpoint.py
aiopika_macrobase/rpc/exceptions.py
aiopika_macrobase/rpc/request.py