Metadata-Version: 1.0
Name: aiopika-macrobase
Version: 2.0.0
Summary: Aio-pika driver for macrobase framework
Home-page: https://github.com/mbcores/aiopika-macrobase
Author: Alexey Shagaleev
Author-email: alexey.shagaleev@yandex.ru
License: MIT
Platform: UNKNOWN
